kamaji/__init__.py
kamaji/__main__.py
kamaji/bashmd.py
kamaji/css.py
kamaji/html5.py
kamaji/log.py
kamaji/md.py
kamaji/nodes.py
kamaji/svg.py
kamaji/resources/__init__.py
kamaji/resources/code.css
kamaji/resources/favicon.svg
kamaji/resources/howto.md
kamaji/resources/index.md
kamaji/resources/license.md
kamaji/resources/main.css
kamaji/resources/main.js
kamaji/resources/menu.md
kamaji/resources/template.html
kamaji-20220225.dist-info/METADATA
kamaji-20220225.dist-info/WHEEL
kamaji-20220225.dist-info/entry_points.txt
kamaji-20220225.dist-info/top_level.txt
kamaji-20220225.dist-info/RECORD
