Metadata-Version: 2.1
Name: kamaji
Version: 20220225
Summary: A static website generator
Home-page: https://code.abelbeck.info/projects/kamaji.html
Author: Frank Abelbeck
Author-email: kamaji@abelbeck.info
License: UNKNOWN
Platform: UNKNOWN
Classifier: Programming Language :: Python :: 3
Classifier: License :: OSI Approved :: GNU General Public License v3 (GPLv3)
Classifier: Operating System :: POSIX :: Linux
Classifier: Environment :: Console
Classifier: Development Status :: 4 - Beta
Classifier: Topic :: Text Processing :: Markup
Requires-Python: >=3.9
Requires-Dist: tinycss2
Requires-Dist: html5lib
Requires-Dist: markdown
Requires-Dist: python-magic
